lightray/__init__.py
lightray/callbacks.py
lightray/cli.py
lightray/fs.py
lightray/utils.py
lightray-0.2.4.dist-info/METADATA
lightray-0.2.4.dist-info/WHEEL
lightray-0.2.4.dist-info/entry_points.txt
lightray-0.2.4.dist-info/RECORD
