Metadata-Version: 2.4
Name: lightray
Version: 0.2.4
Summary: Distribute a LightningCLI hyperparameter search with Ray Tune
Author-email: Ethan Jacob Marx <ethan.marx@ligo.org>
License-Expression: MIT
Requires-Python: ~=3.9
Requires-Dist: jsonargparse[signatures]<5,>=4.33.2
Requires-Dist: lightning>=2.4.0
Requires-Dist: omegaconf<3,>=2.3.0
Requires-Dist: pyarrow<18,>=17.0.0
Requires-Dist: ray[default,tune]<3,>=2.8.0
Requires-Dist: s3fs<2025,>=2024.9.0
Requires-Dist: wandb<0.19,>=0.18.5
